{
  "name": "zra-sandbox",
  "description": "ZRA Sandbox Network Profile",
  "type": "fabric",
  "version": "2.4",
  "client": {
    "organization": "ZRA",
    "connection": {
      "timeout": {
        "peer": {
          "endorser": "300"
        }
      }
    }
  },
  "organizations": {
    "ZRA": {
      "mspid": "ZRAMSP",
      "peers": [
        "peer0.zra.sandbox"
      ],
      "certificateAuthorities": [
        "ca.zra.sandbox"
      ]
    }
  },
  "orderers": {
    "orderer.sandbox": {
      "url": "grpcs://orderer.sandbox.zra.gov.zm:7050",
      "tlsCACerts": {
        "path": "./crypto-config/ordererOrganizations/sandbox.zra.gov.zm/tlsca/tlsca.sandbox.zra.gov.zm-cert.pem"
      }
    }
  },
  "peers": {
    "peer0.zra.sandbox": {
      "url": "grpcs://peer0.zra.sandbox.zra.gov.zm:7051",
      "tlsCACerts": {
        "path": "./crypto-config/peerOrganizations/zra.sandbox.zra.gov.zm/tlsca/tlsca.zra.sandbox.zra.gov.zm-cert.pem"
      }
    }
  },
  "certificateAuthorities": {
    "ca.zra.sandbox": {
      "url": "https://ca.zra.sandbox.zra.gov.zm:7054",
      "caName": "ca-zra",
      "tlsCACerts": {
        "path": "./crypto-config/peerOrganizations/zra.sandbox.zra.gov.zm/ca/ca.zra.sandbox.zra.gov.zm-cert.pem"
      }
    }
  }
}
